fiaprintf/__init__.py
fiaprintf/color.py
fiaprintf/printf.py
printf/__init__.py
printf/color.py
printf/printf.py
fiaprintf-1.0.2.dist-info/METADATA
fiaprintf-1.0.2.dist-info/WHEEL
fiaprintf-1.0.2.dist-info/licence.txt
fiaprintf-1.0.2.dist-info/top_level.txt
fiaprintf-1.0.2.dist-info/RECORD
