Metadata-Version: 2.1
Name: fiaprintf
Version: 1.0.2
Summary: Easy print() with color
Home-page: UNKNOWN
Author: fiachia
Author-email: 208473302@qq.com
Maintainer: fiachia
Maintainer-email: 208473302@qq.com
License: BSD License
Platform: all
License-File: licence.txt
